sentinel_django/__init__.py
sentinel_django/auth.py
sentinel_django/handlers.py
sentinel_django/network.py
sentinel_django-0.1.3.dist-info/LICENSE
sentinel_django-0.1.3.dist-info/WHEEL
sentinel_django-0.1.3.dist-info/METADATA
sentinel_django-0.1.3.dist-info/RECORD
