Metadata-Version: 2.1
Name: sentinel-django
Version: 0.1.3
Summary: Error Detection Package for Sentinel
License: MIT
Author: Niranjan
Author-email: niranjannb7777@gmail.com
Requires-Python: >=3.9,<4.0
Classifier: License :: OSI Approved :: MIT License
Classifier: Programming Language :: Python :: 3
Classifier: Programming Language :: Python :: 3.9
Classifier: Programming Language :: Python :: 3.10
Requires-Dist: Django (==4.0.6)
Requires-Dist: asgiref (==3.5.2)
Requires-Dist: certifi (==2022.6.15)
Requires-Dist: charset-normalizer (==2.1.0)
Requires-Dist: idna (==3.3)
Requires-Dist: requests (==2.28.1)
Requires-Dist: sqlparse (==0.4.2)
Requires-Dist: tzdata (==2022.1)
Requires-Dist: urllib3 (==1.26.11)
